aiopixiv/__init__.py
aiopixiv/v5.py
aiopixiv/wrapper.py
aiopixiv-1.0.5.dist-info/DESCRIPTION.rst
aiopixiv-1.0.5.dist-info/METADATA
aiopixiv-1.0.5.dist-info/RECORD
aiopixiv-1.0.5.dist-info/WHEEL
aiopixiv-1.0.5.dist-info/metadata.json
aiopixiv-1.0.5.dist-info/top_level.txt
