Metadata-Version: 2.0
Name: aiopixiv
Version: 1.0.5
Summary: An asyncio wrapper for the Pixiv API.
Home-page: https://github.com/SunDwarf/aiopixiv
Author: Isaac Dickinson
Author-email: sun@veriny.tf
License: MIT
Platform: UNKNOWN
Requires-Dist: aiohttp (<=2.0.4,>=2.0.0)
